{
  "Directories_Changes": [
    {
      "sign": "?",
      "old_path": "foldertwo",
      "new_path": "foldertwo"
    },
    {
      "sign": "+",
      "path": "foldertwo\\foldertwo"
    }
  ],
  "Changes": [
    {
      "foldertwo-foldertwo": [
        {
          "Sign": "-",
          "name": "itamar.txt"
        },
        {
          "Sign": "-",
          "name": "ramatie.txt"
        }
      ]
    },
    {
      "-foldertwo\\foldertwo": [
        {
          "Sign": "+",
          "name": "proof.txt",
          "Hash": "54efd9114a810f8b8ffccc70d558d8d147fe759df413c049eb54a69125092269"
        }
      ]
    }
  ]
}