{
  "changed_folders": [
    {
      "sign": "+",
      "path": "morefolder"
    },
    {
      "sign": "?",
      "path": ""
    }
  ],
  "changed_files": {
    "morefolder": [
      {
        "sign": "+",
        "new_name": "adir.txt",
        "old_name": null,
        "hash": "947eea6e89cf16ab9836c4d64d3b429a7402583bf8fc77cdb5d9a2565f910447"
      }
    ],
    "": [
      {
        "sign": "+",
        "new_name": "citiesHello.txt",
        "old_name": null,
        "hash": "350465b30c014b0ee38d682b89b8e999de1b9266106d3801fd22ee705594c43e"
      },
      {
        "sign": "+",
        "new_name": "drip.txt",
        "old_name": null,
        "hash": "e3b0c44298fc1c149afbf4c8996fb92427ae41e4649b934ca495991b7852b855"
      }
    ]
  }
}